neritya_clock/__init__.py
neritya_clock/main.py
neritya_clock/resources.py
neritya_clock/fonts/Gameshow.ttf
neritya_clock/fonts/__init.__.py
neritya_clock-2.0.0.dist-info/METADATA
neritya_clock-2.0.0.dist-info/WHEEL
neritya_clock-2.0.0.dist-info/entry_points.txt
neritya_clock-2.0.0.dist-info/top_level.txt
neritya_clock-2.0.0.dist-info/RECORD
