Metadata-Version: 2.4
Name: neritya-clock
Version: 2.0.0
Summary: A fullscreen digital clock with style.
Author-email: Your Name <you@example.com>
License: MIT
Requires-Python: >=3.8
Requires-Dist: PySide6>=6.0.0
